mouseinfolinux/__init__.py
mouseinfolinux/__main__.py
mouseinfolinux/main.py
mouseinfolinux-0.1.0.dist-info/METADATA
mouseinfolinux-0.1.0.dist-info/WHEEL
mouseinfolinux-0.1.0.dist-info/entry_points.txt
mouseinfolinux-0.1.0.dist-info/top_level.txt
mouseinfolinux-0.1.0.dist-info/RECORD
