Metadata-Version: 2.4
Name: mouseinfolinux
Version: 0.1.0
Summary: Ferramenta GTK para inspeção de coordenadas e cores do mouse no Linux.
Requires-Python: >=3.8
Requires-Dist: pygobject
Requires-Dist: python-xlib
